pkg_about/__about__.py
pkg_about/__init__.py
pkg_about/_about.py
pkg_about/py.typed
pkg_about-2.0.11.dist-info/licenses/LICENSE
pkg_about-2.0.11.dist-info/METADATA
pkg_about-2.0.11.dist-info/WHEEL
pkg_about-2.0.11.dist-info/top_level.txt
pkg_about-2.0.11.dist-info/zip-safe
pkg_about-2.0.11.dist-info/RECORD
